postkit/__init__.py
postkit/authn/__init__.py
postkit/authn/client.py
postkit/authz/__init__.py
postkit/authz/client.py
postkit-0.1.0.dist-info/METADATA
postkit-0.1.0.dist-info/WHEEL
postkit-0.1.0.dist-info/RECORD
