Metadata-Version: 2.4
Name: postkit
Version: 0.1.0
Summary: PostgreSQL-native authentication and authorization SDK
Project-URL: Homepage, https://github.com/varunchopra/postkit
Project-URL: Repository, https://github.com/varunchopra/postkit
Author: Varun Chopra
License-Expression: Apache-2.0
Keywords: authentication,authorization,postgresql,rebac,sdk
Classifier: Development Status :: 4 - Beta
Classifier: Intended Audience :: Developers
Classifier: License :: OSI Approved :: Apache Software License
Classifier: Programming Language :: Python :: 3
Classifier: Programming Language :: Python :: 3.10
Classifier: Programming Language :: Python :: 3.11
Classifier: Programming Language :: Python :: 3.12
Classifier: Programming Language :: Python :: 3.13
Classifier: Topic :: Database
Classifier: Topic :: Security
Requires-Python: >=3.10
Requires-Dist: psycopg>=3.1.0
Provides-Extra: binary
Requires-Dist: psycopg[binary]>=3.1.0; extra == 'binary'
Provides-Extra: dev
Requires-Dist: psycopg[binary]>=3.1.0; extra == 'dev'
Requires-Dist: pytest>=7.0; extra == 'dev'
